{
  "total_entries": 14496719,
  "regular_entries": 0,
  "irregular_entries": 0,
  "total_shows": 49,
  "total_callsigns": 96,
  "all_callsigns": [
    "WEVN",
    "WUAL",
    "WNCK",
    "WJCT",
    "KJZZ",
    "WVOC",
    "KTDH",
    "KABQ",
    "KABC",
    "WUWG",
    "WSGN",
    "WBZ",
    "KRLA",
    "WSB",
    "KOGO",
    "KPCC",
    "WPLN-FM",
    "WYAY",
    "WAPR",
    "WOR",
    "KALW",
    "WORT",
    "WESU",
    "WEAN",
    "KRCC",
    "WCPN",
    "WMPN",
    "WFCR",
    "WPRO",
    "KSL",
    "WMFE",
    "KAWC",
    "WUSF",
    "WNAX",
    "WFAW",
    "KUNR",
    "WESA",
    "KNAQ",
    "WNNZ",
    "KTRH",
    "KQED",
    "KPUB",
    "KUAZ",
    "KFMB",
    "KNAG",
    "WURC",
    "WERC",
    "WAMC",
    "WKNO",
    "WHMQ",
    "WMBR",
    "WCSF",
    "KXEL",
    "WABE",
    "KUYI",
    "WTAG",
    "WELH",
    "WRUR",
    "KQNA",
    "KLXX",
    "KJZK",
    "KJZA",
    "KFAB",
    "WJAG",
    "KZSE",
    "WKNP",
    "KJZP",
    "WBUR",
    "KTAR",
    "WHA",
    "WWTN",
    "WBUA",
    "KAWP",
    "WTMJ",
    "KKPC",
    "WBCF",
    "KWSU",
    "WNRI",
    "KUHF",
    "KBUL",
    "WZAI",
    "KBLU",
    "WNGH",
    "WBSM",
    "KVEL",
    "WNBM",
    "WMT",
    "WVYA",
    "KEMC",
    "KIDJ",
    "KUT",
    "WSBB",
    "KRFA",
    "WLTR",
    "KIDG",
    "KIRO"
  ]
}